NuminousAI/AIBase.py
NuminousAI/__init__.py
NuminousAI-1.0.0.dist-info/METADATA
NuminousAI-1.0.0.dist-info/WHEEL
NuminousAI-1.0.0.dist-info/top_level.txt
NuminousAI-1.0.0.dist-info/RECORD
