Metadata-Version: 2.1
Name: NuminousAI
Version: 1.0.0
Summary: This Python package designed to provide a comprehensive interface for interacting with various AI models and performing a range of functionalities such as URL interaction, system command execution, and more.
Author: Sujal Rajpoot
Author-email: sujalrajpoot70@gmail.com
Classifier: Development Status :: 4 - Beta
Classifier: Intended Audience :: Developers
Classifier: Programming Language :: Python :: 3
Classifier: License :: OSI Approved :: MIT License
Classifier: Operating System :: OS Independent
Requires-Python: >=3.6
Requires-Dist: requests >=2.0.0
Requires-Dist: click >=8.1.7
Requires-Dist: appdirs >=1.4.4
Requires-Dist: tqdm >=4.66.4
Requires-Dist: selenium >=4.20.0
Requires-Dist: cerebras-cloud-sdk >=1.5.0
